Workbook

Sheet README
A1: Margin and Collateral Optimization Engine (Excel companion)
A3: Inputs: all assumptions. IM: SIMM-style initial margin, live formulas. Collateral: inventory and haircuts.
A4: Allocation: the linear-program solution pasted from Python (Solver is not required), with live checks.
A5: Scenarios: static results from the Python scenario runs.
A6: SIMM-style means simplified and illustrative. It is not ISDA SIMM and not ISDA certified.
A7: To re-optimize after changing inputs, run python/run_all.py and paste the new allocation, or use Excel Solver.

Sheet Inputs
A1: Market snapshot | B1: Value
A2: AAPL price | B2: 341.07
A3: JPM price | B3: 343.06
A4: XOM price | B4: 160.59
A5: EURUSD | B5: 1.1401
A6: US 10Y yield | B6: 0.0518
A7: Duration proxy (years) | B7: 10
A9: Netting set positions | B9: Counterparty A (equity-heavy) | C9: Counterparty B (rates-heavy)
A10: AAPL shares | B10: 3000 | C10: 0
A11: JPM shares | B11: 2000 | C11: 0
A12: XOM shares | B12: 0 | C12: 500
A13: EUR notional | B13: 5000000 | C13: 1000000
A14: USD rate notional | B14: 30000000 | C14: 80000000
A16: Risk weights | B16: Value
A17: Equity | B17: 0.24
A18: FX | B18: 0.155
A19: Rate | B19: 0.019
A20: Cross-class correlation | B20: 0.3
A21: Cash opportunity cost (bps) | B21: 450

Sheet IM
A1: Item | B1: Counterparty A (equity-heavy) | C1: Counterparty B (rates-heavy)
A2: Equity delta (USD) | B2: =Inputs!B10*Inputs!$B$2+Inputs!B11*Inputs!$B$3+Inputs!B12*Inputs!$B$4 -> 1709330 | C2: =Inputs!C10*Inputs!$B$2+Inputs!C11*Inputs!$B$3+Inputs!C12*Inputs!$B$4 -> 80295
A3: FX delta (USD) | B3: =Inputs!B13*Inputs!$B$5 -> 5700500 | C3: =Inputs!C13*Inputs!$B$5 -> 1140100
A4: Rate exposure (USD, duration-style) | B4: =Inputs!B14*Inputs!$B$7/(1+Inputs!$B$6) -> 2.8522533e+08 | C4: =Inputs!C14*Inputs!$B$7/(1+Inputs!$B$6) -> 7.6060087e+08
A5: Weighted equity | B5: =ABS(B2)*Inputs!$B$17 -> 410239.2 | C5: =ABS(C2)*Inputs!$B$17 -> 19270.8
A6: Weighted FX | B6: =ABS(B3)*Inputs!$B$18 -> 883577.5 | C6: =ABS(C3)*Inputs!$B$18 -> 176715.5
A7: Weighted rate | B7: =ABS(B4)*Inputs!$B$19 -> 5419281.2 | C7: =ABS(C4)*Inputs!$B$19 -> 14451417
A8: Initial margin | B8: =SQRT(B5^2+B6^2+B7^2+2*Inputs!$B$20*(B5*B6+B5*B7+B6*B7)) -> 5894237.5 | C8: =SQRT(C5^2+C6^2+C7^2+2*Inputs!$B$20*(C5*C6+C5*C7+C6*C7)) -> 14511253
A10: Total initial margin | B10: =B8+C8 -> 20405490

Sheet Collateral
A1: Asset | B1: Market value | C1: Haircut | D1: Opportunity cost (bps) | E1: Eligible A | F1: Eligible B | G1: Post-haircut value | H1: Cost per unit of coverage (bps)
A2: Cash (USD) | B2: 15000000 | C2: 0 | D2: 450 | E2: Yes | F2: Yes | G2: =B2*(1-C2) -> 15000000 | H2: =D2/(1-C2) -> 450
A3: US Treasury <1Y | B3: 20000000 | C3: 0.005 | D3: 15 | E3: Yes | F3: Yes | G3: =B3*(1-C3) -> 19900000 | H3: =D3/(1-C3) -> 15.075377
A4: US Treasury 1-5Y | B4: 25000000 | C4: 0.02 | D4: 25 | E4: Yes | F4: Yes | G4: =B4*(1-C4) -> 24500000 | H4: =D4/(1-C4) -> 25.510204
A5: US Treasury 5-10Y | B5: 15000000 | C5: 0.04 | D5: 35 | E5: Yes | F5: Yes | G5: =B5*(1-C5) -> 14400000 | H5: =D5/(1-C5) -> 36.458333
A6: IG Corporate Bonds | B6: 10000000 | C6: 0.08 | D6: 55 | E6: Yes | F6: No | G6: =B6*(1-C6) -> 9200000 | H6: =D6/(1-C6) -> 59.782609
A7: Equities (large-cap) | B7: 8000000 | C7: 0.15 | D7: 80 | E7: No | F7: No | G7: =B7*(1-C7) -> 6800000 | H7: =D7/(1-C7) -> 94.117647

Sheet Allocation
A1: Asset | B1: Posted to A (market value) | C1: Posted to B (market value) | D1: Total posted | E1: Within inventory? | F1: Annual cost
A2: Cash (USD) | B2: 0 | C2: 0 | D2: =B2+C2 -> 0 | E2: =IF(D2<=Collateral!B2+0.01,"OK","BREACH") -> OK | F2: =D2*Collateral!D2/10000 -> 0
A3: US Treasury <1Y | B3: 5923856.7 | C3: 14076143 | D3: =B3+C3 -> 20000000 | E3: =IF(D3<=Collateral!B3+0.01,"OK","BREACH") -> OK | F3: =D3*Collateral!D3/10000 -> 30000
A4: US Treasury 1-5Y | B4: 0 | C4: 515806.23 | D4: =B4+C4 -> 515806.23 | E4: =IF(D4<=Collateral!B4+0.01,"OK","BREACH") -> OK | F4: =D4*Collateral!D4/10000 -> 1289.5156
A5: US Treasury 5-10Y | B5: 0 | C5: 0 | D5: =B5+C5 -> 0 | E5: =IF(D5<=Collateral!B5+0.01,"OK","BREACH") -> OK | F5: =D5*Collateral!D5/10000 -> 0
A6: IG Corporate Bonds | B6: 0 | C6: 0 | D6: =B6+C6 -> 0 | E6: =IF(D6<=Collateral!B6+0.01,"OK","BREACH") -> OK | F6: =D6*Collateral!D6/10000 -> 0
A7: Equities (large-cap) | B7: 0 | C7: 0 | D7: =B7+C7 -> 0 | E7: =IF(D7<=Collateral!B7+0.01,"OK","BREACH") -> OK | F7: =D7*Collateral!D7/10000 -> 0
A9: Coverage to A (post-haircut) | B9: =SUMPRODUCT(B2:B7,1-Collateral!C2:C7) -> 5894237.5
A10: Initial margin A | B10: =IM!B8 -> 5894237.5
A11: A covered? | B11: =IF(B9>=B10-1,"OK","SHORT") -> OK
A12: Coverage to B (post-haircut) | B12: =SUMPRODUCT(C2:C7,1-Collateral!C2:C7) -> 14511253
A13: Initial margin B | B13: =IM!C8 -> 14511253
A14: B covered? | B14: =IF(B12>=B13-1,"OK","SHORT") -> OK
A16: Optimized annual cost | B16: =SUM(F2:F7) -> 31289.516
A17: Cash-only annual cost | B17: =IM!B10*Inputs!B21/10000 -> 918247.05
A18: Annual saving | B18: =B17-B16 -> 886957.54
A19: Saving percent | B19: =B18/B17 -> 0.96592473

Sheet Scenarios
A1: Funding rate sweep (static, from Python)
A2: cash_cost_bps | B2: naive_cost | C2: optimized_cost | D2: saving | E2: saving_pct
A3: 50 | B3: 102027.45 | C3: 31289.516 | D3: 70737.935 | E3: 0.69332258
A4: 100 | B4: 204054.9 | C4: 31289.516 | D4: 172765.39 | E4: 0.84666129
A5: 200 | B5: 408109.8 | C5: 31289.516 | D5: 376820.29 | E5: 0.92333064
A6: 300 | B6: 612164.7 | C6: 31289.516 | D6: 580875.19 | E6: 0.9488871
A7: 450 | B7: 918247.05 | C7: 31289.516 | D7: 886957.54 | E7: 0.96592473
A8: 600 | B8: 1224329.4 | C8: 31289.516 | D8: 1193039.9 | E8: 0.97444355
A11: Haircut stress (static, from Python)
A12: haircut_multiplier | B12: optimized_cost | C12: market_value_posted | D12: overcollateral_pct
A13: 1 | B13: 31289.516 | C13: 20515806 | D13: 0.0054061982
A14: 1.5 | B14: 31431.676 | C14: 20572670 | D14: 0.0081928984
A15: 2 | B15: 31576.797 | C15: 20630719 | D15: 0.011037655
A16: 3 | B16: 31876.303 | C16: 20750521 | D16: 0.016908748
A19: Initial margin scaling (static, from Python)
A20: im_scale | B20: total_im | C20: feasible | D20: optimized_cost | E20: shadow_price_a | F20: shadow_price_b
A21: 0.5 | B21: 10202745 | C21: =TRUE() -> TRUE | D21: 15381.023 | E21: 0.0015075377 | F21: 0.0015075377
A22: 1 | B22: 20405490 | C22: =TRUE() -> TRUE | D22: 31289.516 | E22: 0.0025510204 | F22: 0.0025510204
A23: 1.5 | B23: 30608235 | C23: =TRUE() -> TRUE | D23: 57316.926 | E23: 0.0025510204 | F23: 0.0025510204
A24: 2 | B24: 40810980 | C24: =TRUE() -> TRUE | D24: 83344.337 | E24: 0.0025510204 | F24: 0.0025510204
A25: 2.5 | B25: 51013725 | C25: =TRUE() -> TRUE | D25: 116612.54 | E25: 0.0036458333 | F25: 0.0036458333
A26: 3 | B26: 61216470 | C26: =TRUE() -> TRUE | D26: 159446.29 | E26: 0.0059782609 | F26: 0.0059782609
A29: Treasury scarcity (static, from Python)
A30: treasury_availability | B30: feasible | C30: optimized_cost | D30: cash_posted
A31: 1 | B31: =TRUE() -> TRUE | C31: 31289.516 | D31: 0
A32: 0.75 | B32: =TRUE() -> TRUE | C32: 36480.842 | D32: 0
A33: 0.5 | B33: =TRUE() -> TRUE | C33: 41672.169 | D33: 0
A34: 0.25 | B34: =TRUE() -> TRUE | C34: 70358.908 | D34: 0
A35: 0.1 | B35: =TRUE() -> TRUE | C35: 438143.66 | D35: 8631252.6
A38: Eligibility cases (static, from Python)
A39: case | B39: optimized_cost
A40: Base (Treasuries <1Y eligible for both) | B40: 31289.516
A41: Treasuries <1Y ineligible for B | B41: 45904.287
A42: Treasuries <1Y ineligible for both | B42: 52054.822
